validate_plist_xml/__init__.py
validate_plist_xml/__main__.py
validate_plist_xml/validate_plist_xml.py
validate_plist_xml-1.0.4.dist-info/LICENSE
validate_plist_xml-1.0.4.dist-info/METADATA
validate_plist_xml-1.0.4.dist-info/WHEEL
validate_plist_xml-1.0.4.dist-info/top_level.txt
validate_plist_xml-1.0.4.dist-info/RECORD
